{
  "id": "BP23334031",
  "businessPartnerNumber": "BP23334031",
  "category": "2",
  "roles": [
    "FLSP00"
  ],
  "industrySector": "Z005",
  "customerClassification": "A",
  "createdAt": "2022-01-21",
  "lastModified": "2025-02-21",
  "organizationName": "Trantow - Schaden",
  "organizationType": "LLC",
  "industryKey": "UTIL",
  "foundationDate": "2013-11-13",
  "legalForm": "AG",
  "vatNumber": "NESIPECJUD",
  "taxNumber": "168106847",
  "__secure": [
    "firstName",
    "lastName",
    "birthDate",
    "nationalId"
  ]
}