{
  "id": "BP45575413",
  "businessPartnerNumber": "BP45575413",
  "category": "1",
  "roles": [
    "FLSP00"
  ],
  "industrySector": "Z004",
  "customerClassification": "C",
  "createdAt": "2021-09-13",
  "lastModified": "2025-01-16",
  "firstName": "966cc77d57e7b4ffa05d823ea3d682a2",
  "lastName": "d977221c4cae6dbcb1110c34d8645322",
  "gender": "Intersex man",
  "birthDate": "d98d5b011993e3356284d89f82a45901",
  "nationality": "MZ",
  "maritalStatus": "DIVORCED",
  "__secure": [
    "firstName",
    "lastName",
    "birthDate",
    "nationalId"
  ]
}