[
  [
    {
      "type": "EMAIL",
      "value": "Lolita95@yahoo.com",
      "isPrimary": true,
      "validFrom": "2024-08-31"
    },
    {
      "type": "PHONE",
      "value": "(905) 347-2541 x3444",
      "isPrimary": true,
      "validFrom": "2024-08-15"
    },
    {
      "type": "MOBILE",
      "value": "(955) 535-6520 x70126",
      "isPrimary": false,
      "validFrom": "2024-06-17"
    },
    {
      "type": "FAX",
      "value": "600.998.3359",
      "isPrimary": false,
      "validFrom": "2024-05-23"
    }
  ]
]