[
  [
    {
      "street": "Lilian Overpass",
      "houseNumber": "667",
      "postalCode": "31624-9026",
      "city": "West Haven",
      "country": "IL",
      "region": "WEST",
      "addressType": "BILL",
      "validFrom": "2024-03-19"
    },
    {
      "street": "Brayan Turnpike",
      "houseNumber": "521",
      "postalCode": "88039-8946",
      "city": "Hymanboro",
      "country": "AD",
      "region": "NORTH",
      "addressType": "INST",
      "validFrom": "2021-10-30"
    }
  ]
]